onetouchlite/__init__.py
onetouchlite/tools/__init__.py
onetouchlite/tools/superprint.py
onetouchlite/tools/timer.py
onetouchlite/utils/libprogress.so
onetouchlite/utils/progress.dll
onetouchlite-0.0.8.dist-info/METADATA
onetouchlite-0.0.8.dist-info/WHEEL
onetouchlite-0.0.8.dist-info/top_level.txt
onetouchlite-0.0.8.dist-info/RECORD
