Metadata-Version: 2.2
Name: onetouchlite
Version: 0.0.8
Summary: 一个简单的轻量，集成了大多数OneTouch用法的工具包
Home-page: https://gitee.com/SunnyB0y/onetouch
Author: 17fine
Author-email: 2756601885@qq.com
Classifier: Programming Language :: Python :: 3
Classifier: License :: OSI Approved :: MIT License
Classifier: Operating System :: OS Independent
Requires-Python: >=3.6
Dynamic: author
Dynamic: author-email
Dynamic: classifier
Dynamic: description
Dynamic: description-content-type
Dynamic: home-page
Dynamic: requires-python
Dynamic: summary
